xyz_canvas/__init__.py
xyz_canvas/canvas.py
xyz_canvas-1.1.2.dist-info/licenses/LICENSE
xyz_canvas-1.1.2.dist-info/METADATA
xyz_canvas-1.1.2.dist-info/WHEEL
xyz_canvas-1.1.2.dist-info/top_level.txt
xyz_canvas-1.1.2.dist-info/RECORD
