Metadata-Version: 2.4
Name: xyz_canvas
Version: 1.1.2
Summary: Interactive canvas for editing 3D geometry, using matplotlib.pyplot
Author-email: G1OJS <g1ojs@yahoo.com>
License-Expression: MIT
Project-URL: Homepage, https://github.com/G1OJS/xyz_canvas
Project-URL: Issues, https://github.com/G1OJS/xyz_canvas/issues
Keywords: 3D,Matplotlib,Geometry,GUI,Canvas,Wire frame,minimal,lightweight
Classifier: Programming Language :: Python :: 3
Classifier: Operating System :: OS Independent
Classifier: Development Status :: 5 - Production/Stable
Classifier: Intended Audience :: Science/Research
Classifier: Topic :: Scientific/Engineering :: Visualization
Classifier: Intended Audience :: Developers
Classifier: Topic :: Multimedia :: Graphics :: Editors
Requires-Python: >=3.8
License-File: LICENSE
Requires-Dist: matplotlib
Dynamic: license-file
